pkv/__init__.py
pkv/main.py
pkv-1.0.2.dist-info/LICENSE
pkv-1.0.2.dist-info/METADATA
pkv-1.0.2.dist-info/WHEEL
pkv-1.0.2.dist-info/top_level.txt
pkv-1.0.2.dist-info/RECORD
