Metadata-Version: 2.1
Name: pkv
Version: 1.0.2
Summary: A minimalistic persistent key value store.
Home-page: UNKNOWN
Author: Jayjeet Chakraborty
Author-email: jayjeetchakraborty25@gmail.com
License: MIT
Platform: UNKNOWN
Requires-Dist: pyyaml
